bigwing/__init__.py
bigwing/api.py
bigwing/crawler.py
bigwing/db.py
bigwing/search.py
bigwing/browser/chromedriver.exe
bigwing/browser/phantomjs.exe
bigwing-1.4.3.dist-info/METADATA
bigwing-1.4.3.dist-info/WHEEL
bigwing-1.4.3.dist-info/license.md
bigwing-1.4.3.dist-info/top_level.txt
bigwing-1.4.3.dist-info/RECORD
